pyaurorax/__init__.py
pyaurorax/_util.py
pyaurorax/cli/__init__.py
pyaurorax/cli/cli.py
pyaurorax/cli/search/__init__.py
pyaurorax/cli/search/availability/__init__.py
pyaurorax/cli/search/availability/commands.py
pyaurorax/cli/search/conjunctions/__init__.py
pyaurorax/cli/search/conjunctions/commands.py
pyaurorax/cli/search/data_products/__init__.py
pyaurorax/cli/search/data_products/commands.py
pyaurorax/cli/search/ephemeris/__init__.py
pyaurorax/cli/search/ephemeris/commands.py
pyaurorax/cli/search/helpers.py
pyaurorax/cli/search/sources/__init__.py
pyaurorax/cli/search/sources/commands.py
pyaurorax/cli/search/util/__init__.py
pyaurorax/cli/search/util/commands.py
pyaurorax/cli/templates.py
pyaurorax/data/__init__.py
pyaurorax/data/ucalgary/__init__.py
pyaurorax/data/ucalgary/read/__init__.py
pyaurorax/exceptions.py
pyaurorax/models/__init__.py
pyaurorax/models/atm/__init__.py
pyaurorax/pyaurorax.py
pyaurorax/search/__init__.py
pyaurorax/search/api/__init__.py
pyaurorax/search/api/classes/__init__.py
pyaurorax/search/api/classes/request.py
pyaurorax/search/api/classes/response.py
pyaurorax/search/availability/__init__.py
pyaurorax/search/availability/_availability.py
pyaurorax/search/availability/classes/__init__.py
pyaurorax/search/availability/classes/availability_result.py
pyaurorax/search/conjunctions/__init__.py
pyaurorax/search/conjunctions/_conjunctions.py
pyaurorax/search/conjunctions/classes/conjunction.py
pyaurorax/search/conjunctions/classes/criteria_block.py
pyaurorax/search/conjunctions/classes/search.py
pyaurorax/search/conjunctions/swarmaurora/__init__.py
pyaurorax/search/conjunctions/swarmaurora/_swarmaurora.py
pyaurorax/search/data_products/__init__.py
pyaurorax/search/data_products/_data_products.py
pyaurorax/search/data_products/classes/__init__.py
pyaurorax/search/data_products/classes/data_product.py
pyaurorax/search/data_products/classes/search.py
pyaurorax/search/ephemeris/__init__.py
pyaurorax/search/ephemeris/_ephemeris.py
pyaurorax-1.22.0.dist-info/METADATA
pyaurorax-1.22.0.dist-info/WHEEL
pyaurorax-1.22.0.dist-info/entry_points.txt
pyaurorax-1.22.0.dist-info/licenses/LICENSE
pyaurorax-1.22.0.dist-info/RECORD
