Metadata-Version: 2.4
Name: pyaurorax
Version: 1.22.0
Summary: Python library for interacting with the AuroraX platform
License: Apache-2.0
License-File: LICENSE
Keywords: aurorax,space physics,aurora,aurora borealis,northern lights,southern lights
Author: Darren Chaddock
Author-email: dchaddoc@ucalgary.ca
Maintainer: Darren Chaddock
Maintainer-email: dchaddoc@ucalgary.ca
Requires-Python: >=3.10
Classifier: Intended Audience :: Science/Research
Classifier: License :: OSI Approved :: Apache Software License
Classifier: Natural Language :: English
Classifier: Operating System :: MacOS :: MacOS X
Classifier: Operating System :: Microsoft :: Windows
Classifier: Operating System :: POSIX :: Linux
Classifier: Programming Language :: Python :: 3
Classifier: Programming Language :: Python :: 3.10
Classifier: Programming Language :: Python :: 3.11
Classifier: Programming Language :: Python :: 3.12
Classifier: Programming Language :: Python :: 3.13
Classifier: Programming Language :: Python :: 3.14
Classifier: Topic :: Scientific/Engineering
Classifier: Topic :: Scientific/Engineering :: Physics
Classifier: Topic :: Software Development :: Libraries
Requires-Dist: aacgmv2 (>=2.6.2,<3.0.0)
Requires-Dist: cartopy (>=0.24.0,<1.0.0) ; python_version >= "3.10"
Requires-Dist: click (>=8.1.3,<9.0.0)
Requires-Dist: humanize (>=4.4.0,<5.0.0)
Requires-Dist: matplotlib (>=3.5.0,<4.0.0) ; python_version >= "3.10"
Requires-Dist: numpy (>=1.21.0,<2.3.0) ; python_version == "3.10"
Requires-Dist: numpy (>=1.21.0,<3.0.0) ; python_version >= "3.11"
Requires-Dist: pyproj (>=3.7.0,<4.0.0) ; python_version >= "3.10"
Requires-Dist: python-dateutil (>=2.8.2,<3.0.0)
Requires-Dist: pyucalgarysrs (>=1.26.0,<2.0.0)
Requires-Dist: requests (>=2.28.1,<3.0.0)
Requires-Dist: scipy (>=1.10)
Requires-Dist: termcolor (>=2.0.1)
Requires-Dist: texttable (>=1.6.4,<2.0.0)
Project-URL: API Reference, https://docs.aurorax.space/code/pyaurorax_api_reference/pyaurorax
Project-URL: AuroraX Platform, https://aurorax.space
Project-URL: Homepage, https://github.com/aurorax-space/pyaurorax
Project-URL: Repository, https://github.com/aurorax-space/pyaurorax
Project-URL: UCalgary SRS Open Data Platform, https://data.phys.ucalgary.ca
